bzutech/__init__.py
bzutech/bzutechapi/BzuTechAPI.py
bzutech/bzutechapi/__init__.py
bzutech/device/Device.py
bzutech/device/__init__.py
bzutech/sensor/Sensor.py
bzutech/sensor/__init__.py
bzutech-2.3.4.dist-info/METADATA
bzutech-2.3.4.dist-info/WHEEL
bzutech-2.3.4.dist-info/licenses/LICENSE.md
bzutech-2.3.4.dist-info/RECORD
